README.md
setup.py
Greendeck/__init__.py
Greendeck_ukanhaupa.egg-info/PKG-INFO
Greendeck_ukanhaupa.egg-info/SOURCES.txt
Greendeck_ukanhaupa.egg-info/dependency_links.txt
Greendeck_ukanhaupa.egg-info/top_level.txt