Metadata-Version: 2.1
Name: Greendeck-ukanhaupa
Version: 0.0.1
Summary: greendeck assignment package
Home-page: https://github.com/ukanhaupa/Greendeck
Author: Kanha Upadhyay
Author-email: mr.kanhaupadhyay@gmail.com
License: UNKNOWN
Platform: UNKNOWN
